squaredown/__init__.py
squaredown/catalog.py
squaredown/connector.py
squaredown/i_square.py
squaredown/itemizations.py
squaredown/locations.py
squaredown/logging_config.json
squaredown/orders.py
squaredown/payouts.py
squaredown/report_data.py
squaredown-1.7.4.dist-info/METADATA
squaredown-1.7.4.dist-info/WHEEL
squaredown-1.7.4.dist-info/licenses/LICENSE
squaredown-1.7.4.dist-info/RECORD
