Metadata-Version: 2.4
Name: squaredown
Version: 1.7.4
Summary: Customized Square interface
License: MIT
License-File: LICENSE
Keywords: python,square,mongodb
Author: Jason Romano
Author-email: aracnid@gmail.com
Requires-Python: >=3.10,<4.0
Classifier: License :: OSI Approved :: MIT License
Classifier: Programming Language :: Python :: 3
Classifier: Programming Language :: Python :: 3.10
Classifier: Programming Language :: Python :: 3.11
Classifier: Programming Language :: Python :: 3.12
Classifier: Programming Language :: Python :: 3.13
Classifier: Programming Language :: Python :: 3.14
Requires-Dist: aracnid-config (>=1.0,<2.0)
Requires-Dist: aracnid-logger (>=1.0,<2.0)
Requires-Dist: aracnid-utils (>=1.0,<2.0)
Requires-Dist: i-mongodb (>=2.0,<3.0)
Requires-Dist: squareup (>=19.1,<20.0)
Requires-Dist: tqdm (>=4.64,<5.0)
Project-URL: Repository, https://github.com/aracnid/squaredown
